hoca/__init__.py
hoca/core/BasicPopulation.py
hoca/core/ImageField.py
hoca/core/ImageFieldorg.py
hoca/core/__init__.py
hoca/core/automata_framework.py
hoca/core/utilities.py
hoca/demo/LiteEdgeAutomaton.py
hoca/demo/SpreadingAutomaton.py
hoca/demo/__init__.py
hoca/monitor/CallbackPopulation.py
hoca/monitor/ColorGradient.py
hoca/monitor/PILMonitor.py
hoca/monitor/__init__.py
hoca-2021.9.0.dist-info/LICENSE
hoca-2021.9.0.dist-info/METADATA
hoca-2021.9.0.dist-info/WHEEL
hoca-2021.9.0.dist-info/top_level.txt
hoca-2021.9.0.dist-info/RECORD
