Metadata-Version: 2.1
Name: hoca
Version: 2021.9.0
Summary: Provides a set of tools to implement Higher-Order Cellular Automata populations
Home-page: https://github.com/g-art-dev/hoca
Author: Jean-Louis Paquelin and Enrico Formenti
Author-email: g-art-dev@villa-arson.org
License: GNU Lesser General Public License v3 or later
Keywords: cellular automata,agents
Platform: UNKNOWN
Classifier: Operating System :: OS Independent
Classifier: Natural Language :: English
Classifier: Intended Audience :: Developers
Classifier: Intended Audience :: Education
Classifier: Intended Audience :: Science/Research
Classifier: Topic :: Software Development
Classifier: Topic :: Software Development :: Libraries
Classifier: Topic :: Software Development :: Libraries :: Python Modules
Classifier: Topic :: Scientific/Engineering
Classifier: Topic :: Scientific/Engineering :: Artificial Life
Classifier: Topic :: Scientific/Engineering :: Image Processing
Classifier: Topic :: Artistic Software
Classifier: Programming Language :: Python :: 3
Classifier: Programming Language :: Python :: 3.7
Classifier: License :: OSI Approved :: GNU Lesser General Public License v3 or later (LGPLv3+)
Requires-Python: >=3
License-File: LICENSE
Requires-Dist: numpy (>=1.20.1)
Requires-Dist: Pillow (>=7.0.0)
Requires-Dist: av (>=8.0.3)
